src/modules/FileRegister.v
// Vamos ter 3 bits livres para endereçar os registradores.
// O que nos permite ter até 8 registradores.
module FileRegister(
    input wire clk, 
    input wire reset, // reseta todos os registradores
    input wire load, // permite trocar dado salvo
    input wire [2:0] address,  // 3 bits para endereçar os registradores
    input wire [7:0] d_in, // entrada de dados
    output reg [7:0] q_out // saída do registrador
);

    reg [7:0] registers [0:7];  // 8 registradores de 8 bits

    always @(posedge clk or posedge reset) begin
        if (reset) begin //zera todos os registradores
            registers[0] <= 8'b0;
            registers[1] <= 8'b0;
            registers[2] <= 8'b0;
            registers[3] <= 8'b0;
            registers[4] <= 8'b0;
            registers[5] <= 8'b0;
            registers[6] <= 8'b0;
            registers[7] <= 8'b0;
        end else if (load) begin
            registers[address] <= d_in;
        end
    end
    
    always @(*) begin
        q_out = registers[address];
    end
endmodule

src/test/registerFile_testbench.v
module registerFile_testbench();

    reg clk;
    reg reset;
    reg load;
    reg [7:0] d_in;
    reg [2:0] address;
    wire [7:0] q_out;

    integer i; // variável auxiliar de controle do loop

    // Instanciando o módulo do registrador
    FileRegister test_register (
        .clk(clk),
        .reset(reset),
        .load(load),
        .address(address), // endereço do registrador
        .d_in(d_in),
        .q_out(q_out)
    );

    // Gera o clock 
    always #5 clk = ~clk; // alterna seu estado em 5 blocos de tempo

    initial begin
        // Configuração para gerar o arquivo .vcd
        $dumpfile("test_FileRegister.vcd");
        $dumpvars(0, registerFile_testbench);

        // Inicializa os sinais
        clk = 0;
        reset = 0;
        load = 0;
        address = 0;
        d_in = 0;

        // Aplica reset
        #10 reset = 1;
        #10 reset = 0;       

        // Teste 1: Carrega um valor em cada registrador
        $display("Test 1...");
        for (i = 0; i < 8; i++) begin
            address = i[2:0]; // endereço do registrador 3 bits menos significativos de i
            load = 1;
            d_in = 8'b10101010+address;
            #10 load = 0;
            #10; //espera pra ver o resultado
            $display("Address: %d, d_in: %b, q_out: %b, load: %b", address, d_in, q_out, load);
        end
        $display("Test 1 done!");

        $display("Test 2...");
        // Teste 2: Coloca outro valor na entrada sem alterar o load
        for (i = 0; i < 8; i++) begin
            #10 d_in = 8'b11001100;
        end
        $display("Test 2 done!");


        $display("Test 3...");
        // Teste 3: Altera o load e varia o endereço para alterar o valor do registrador
        for (i = 0; i < 8; i++) begin
            address = i[2:0];
            #10 load = 1;
        end
        #10 load = 0;
        $display("Test 3 done!");

        $display("Test 4...");
        // Teste 4: Aplica reset (deve zerar o registrador mesmo sem estar na borda positiva do clock)
        #10 reset = 1;
        #10 reset = 0;
        $display("Test 4 done!");

        $display("Test finished! :D");

        #50 $finish;
    end

endmodule

src/test/test_outputs/test_FileRegister.vcd
$date
	Wed Aug 14 08:36:16 2024
$end
$version
	Icarus Verilog
$end
$timescale
	1s
$end
$scope module registerFile_testbench $end
$var wire 8 ! q_out [7:0] $end
$var reg 3 " address [2:0] $end
$var reg 1 # clk $end
$var reg 8 $ d_in [7:0] $end
$var reg 1 % load $end
$var reg 1 & reset $end
$var integer 32 ' i [31:0] $end
$scope module test_register $end
$var wire 3 ( address [2:0] $end
$var wire 1 # clk $end
$var wire 8 ) d_in [7:0] $end
$var wire 1 % load $end
$var wire 1 & reset $end
$var reg 8 * q_out [7:0] $end
$upscope $end
$upscope $end
$enddefinitions $end
#0
$dumpvars
bx *
b0 )
b0 (
bx '
0&
0%
b0 $
0#
b0 "
bx !
$end
#5
1#
#10
b0 !
b0 *
0#
1&
#15
1#
#20
0#
b10101010 $
b10101010 )
1%
b0 '
0&
#25
b10101010 !
b10101010 *
1#
#30
0#
0%
#35
1#
#40
b0 !
b0 *
0#
b10101011 $
b10101011 )
1%
b1 "
b1 (
b1 '
#45
b10101011 !
b10101011 *
1#
#50
0#
0%
#55
1#
#60
b0 !
b0 *
0#
b10101100 $
b10101100 )
1%
b10 "
b10 (
b10 '
#65
b10101100 !
b10101100 *
1#
#70
0#
0%
#75
1#
#80
b0 !
b0 *
0#
b10101101 $
b10101101 )
1%
b11 "
b11 (
b11 '
#85
b10101101 !
b10101101 *
1#
#90
0#
0%
#95
1#
#100
b0 !
b0 *
0#
b10101110 $
b10101110 )
1%
b100 "
b100 (
b100 '
#105
b10101110 !
b10101110 *
1#
#110
0#
0%
#115
1#
#120
b0 !
b0 *
0#
b10101111 $
b10101111 )
1%
b101 "
b101 (
b101 '
#125
b10101111 !
b10101111 *
1#
#130
0#
0%
#135
1#
#140
b0 !
b0 *
0#
b10110000 $
b10110000 )
1%
b110 "
b110 (
b110 '
#145
b10110000 !
b10110000 *
1#
#150
0#
0%
#155
1#
#160
b0 !
b0 *
0#
b10110001 $
b10110001 )
1%
b111 "
b111 (
b111 '
#165
b10110001 !
b10110001 *
1#
#170
0#
0%
#175
1#
#180
0#
b0 '
#185
1#
#190
0#
b1 '
b11001100 $
b11001100 )
#195
1#
#200
0#
b10 '
#205
1#
#210
0#
b11 '
#215
1#
#220
0#
b100 '
#225
1#
#230
0#
b101 '
#235
1#
#240
0#
b110 '
#245
1#
#250
0#
b111 '
#255
1#
#260
b10101010 !
b10101010 *
0#
b0 "
b0 (
b0 '
#265
1#
#270
b10101011 !
b10101011 *
0#
b1 "
b1 (
b1 '
1%
#275
b11001100 !
b11001100 *
1#
#280
b10101100 !
b10101100 *
0#
b10 "
b10 (
b10 '
#285
b11001100 !
b11001100 *
1#
#290
b10101101 !
b10101101 *
0#
b11 "
b11 (
b11 '
#295
b11001100 !
b11001100 *
1#
#300
b10101110 !
b10101110 *
0#
b100 "
b100 (
b100 '
#305
b11001100 !
b11001100 *
1#
#310
b10101111 !
b10101111 *
0#
b101 "
b101 (
b101 '
#315
b11001100 !
b11001100 *
1#
#320
b10110000 !
b10110000 *
0#
b110 "
b110 (
b110 '
#325
b11001100 !
b11001100 *
1#
#330
b10110001 !
b10110001 *
0#
b111 "
b111 (
b111 '
#335
b11001100 !
b11001100 *
1#
#340
0#
b1000 '
#345
1#
#350
0#
0%
#355
1#
#360
b0 !
b0 *
0#
1&
#365
1#
#370
0#
0&
