src/modules/register.v
module register (
    input wire clk,          // Sinal de clock
    input wire reset,        // Sinal de reset
    input wire load,         // Sinal para carregar o valor no registrador
    input wire [7:0] d_in,   // Dados de entrada (8 bits)
    output reg [7:0] q_out   // Dados de saída (8 bits)
);

    // Bloco always sensível ao clock e ao sinal de reset (reset não precisa funcionar na borda do clock)
    always @(posedge clk or posedge reset) begin
        if (reset) begin
            q_out <= 8'b0;   // Zera o registrador em caso de reset
        end else if (load) begin
            q_out <= d_in;   // Carrega o valor de entrada no registrador
        end
    end

endmodule

src/test/register_testbench.v
module register_testbench();

    reg clk;
    reg reset;
    reg load;
    reg [7:0] d_in;
    wire [7:0] q_out;

    // Instanciando o módulo do registrador
    register test_register (
        .clk(clk),
        .reset(reset),
        .load(load),
        .d_in(d_in),
        .q_out(q_out)
    );

    // Gera o clock 
    always #5 clk = ~clk; // alterna seu estado em 5 blocos de tempo

    initial begin
        // Configuração para gerar o arquivo .vcd
        $dumpfile("test_register.vcd");
        $dumpvars(0, register_testbench);

        // Inicializa os sinais
        clk = 0;
        reset = 0;
        load = 0;
        d_in = 8'b0;

        // Aplica reset
        #10 reset = 1;
        #10 reset = 0;

        // Teste 1: Carrega um valor no registrador
        #10 load = 1; d_in = 8'b10101010;
        #10 load = 0;

        // Teste 2: Carrega outro valor no registrador sem mudar o load
        #10 d_in = 8'b11001100;

        // Teste 3: Altera o load para ver mudança no registrador
        #10 load = 1;
        #10 load = 0;

        // Teste 3: Aplica reset (deve zerar o registrador mesmo sem estar na borda positiva do clock)
        #10 reset = 1;
        #10 reset = 0;

        #50 $finish;
    end

endmodule

src/test/test_outputs/test_register.vcd
$date
	Thu Aug  8 15:53:10 2024
$end
$version
	Icarus Verilog
$end
$timescale
	1s
$end
$scope module register_testbench $end
$var wire 8 ! q_out [7:0] $end
$var reg 1 " clk $end
$var reg 8 # d_in [7:0] $end
$var reg 1 $ load $end
$var reg 1 % reset $end
$scope module test_register $end
$var wire 1 " clk $end
$var wire 8 & d_in [7:0] $end
$var wire 1 $ load $end
$var wire 1 % reset $end
$var reg 8 ' q_out [7:0] $end
$upscope $end
$upscope $end
$enddefinitions $end
#0
$dumpvars
bx '
b0 &
0%
0$
b0 #
0"
bx !
$end
#5
1"
#10
b0 !
b0 '
0"
1%
#15
1"
#20
0"
0%
#25
1"
#30
0"
b10101010 #
b10101010 &
1$
#35
b10101010 !
b10101010 '
1"
#40
0"
0$
#45
1"
#50
0"
b11001100 #
b11001100 &
#55
1"
#60
0"
1$
#65
b11001100 !
b11001100 '
1"
#70
0"
0$
#75
1"
#80
b0 !
b0 '
0"
1%
#85
1"
#90
0"
0%
