src/modules/PointCounter.v
module PointCounter (
    input wire clk,
    input wire reset,
    input wire load,
    input wire [7:0] set_value,
    output reg [7:0] points
);

    always @(posedge clk or posedge reset) begin
        if (reset)
            points <= 0;
        else if (load)
            points <= set_value + 1;
        else
            points <= points + 1;
    end

endmodule

src/test/PC_testbench.v
module PC_testbench();

    // Inputs
    reg clk;
    reg reset;
    reg load;
    reg [7:0] set_value;

    // Outputs
    wire [7:0] points;

    // Instantiate the point counter module
    PointCounter point_counter (
        .clk(clk),
        .reset(reset),
        .load(load),
        .set_value(set_value),
        .points(points)
    );

    // Clock generation
    always #5 clk = ~clk;

    // Test stimulus
    initial begin
        // Gerando arquivos .vcd
        $dumpfile("test_PC.vcd");
        $dumpvars(0, PC_testbench);

        // Initialize inputs
        clk = 0;
        reset = 1;
        load = 0;
        set_value = 10;

        // Começa o contador
        #5 reset = 0;

        //  Carrega novo valor no contador
        #15 load = 1;

        // Finaliza com o reset
        #10 load = 0;
        #10 reset = 1;
        
        // Wait for simulation to complete
        #10 $finish;
    end

endmodule

src/test/test_outputs/test_PC.vcd
$date
	Mon Aug 19 15:07:58 2024
$end
$version
	Icarus Verilog
$end
$timescale
	1s
$end
$scope module PC_testbench $end
$var wire 8 ! points [7:0] $end
$var reg 1 " clk $end
$var reg 1 # load $end
$var reg 1 $ reset $end
$var reg 8 % set_value [7:0] $end
$scope module point_counter $end
$var wire 1 " clk $end
$var wire 1 # load $end
$var wire 1 $ reset $end
$var wire 8 & set_value [7:0] $end
$var reg 8 ' points [7:0] $end
$upscope $end
$upscope $end
$enddefinitions $end
#0
$dumpvars
b0 '
b1010 &
b1010 %
1$
0#
0"
b0 !
$end
#5
b1 !
b1 '
0$
1"
#10
0"
#15
b10 !
b10 '
1"
#20
0"
1#
#25
b1010 !
b1010 '
1"
#30
0"
0#
#35
b1011 !
b1011 '
1"
#40
b0 !
b0 '
0"
1$
