src/modules/FileRegister.v
// Vamos ter 3 bits livres para endereçar os registradores.
// O que nos permite ter até 8 registradores.
module FileRegister(
    //Entradas
    input wire clk, 
    input wire reset, // reseta o registrador do endereço addr_a
    input wire reset_all, // reseta todos os registradores
    input wire load, // permite salvar dado no endereço addr_a 
    input wire [2:0] addr_a,  // 3 bits para endereçar os registradores
    input wire [2:0] addr_b,  // 3 bits para endereçar os registradores
    input wire [7:0] d_in, // dado de entrada para o registrador addr_a
    input wire mb_select, // seleciona se val_b vai ser o próprio addr_b ou o dado do registrador
    // Saídas
    output reg [7:0] val_a, // saída do registrador barramento A
    output reg [7:0] val_b // saída do registrador barramento B
);

    reg [7:0] registers [0:7];  // 8 registradores de 8 bits

    integer i; // variável de controle do loop
    always @(posedge clk or posedge reset) begin
        if (reset) begin //zera o registrador no endereço add_a
            registers[addr_a] <= 8'b0;
        
        end else if (reset_all) begin //zera todos os registradores
            for (i = 0; i < 8; i = i + 1) begin
                registers[i] <= 8'b0;
            end
        
        end else if (load) begin // carrega dado no registrador addr_a
            registers[addr_a] <= d_in;
        end
    end
    
    always @(*) begin
        val_a = registers[addr_a];
        if (mb_select) begin
            val_b = addr_b;
        end else
            val_b = registers[addr_b]; 
    end
endmodule

src/test/registerFile_testbench.v
module registerFile_testbench();

    reg clk;
    reg reset;
    reg reset_all;
    reg load;

    reg [2:0] addr_a;
    reg [2:0] addr_b;
    reg [7:0] d_in;
    reg mb_select;
    
    wire [7:0] out_a;
    wire [7:0] out_b;

    integer i; // variável auxiliar de controle do loop

    // Instanciando o módulo do registrador
    FileRegister test_register (
        .clk(clk),
        .reset(reset),
        .reset_all(reset_all),
        .load(load),
        .addr_a(addr_a), // endereço do registrador A
        .addr_b(addr_b), // endereço do registrador B
        .d_in(d_in),
        .mb_select(mb_select), // seleciona se val_b vai ser o dado de entrada ou o dado do registrador
        .val_a(out_a) , // saída do registrador A
        .val_b(out_b) // saída do registrador B
    );

    // Gera o clock 
    always #5 clk = ~clk; // alterna seu estado em 5 blocos de tempo

    initial begin
        // Configuração para gerar o arquivo .vcd
        $dumpfile("test_FileRegister.vcd");
        $dumpvars(0, registerFile_testbench);

        // Inicializa os sinais
        clk = 0;
        reset = 0;
        reset_all = 0;
        load = 0;
        addr_a = 0;
        addr_b = 0;
        d_in = 0;
        mb_select = 0;

        // Aplica reset_all
        #10 reset_all = 1;
        #10 reset_all = 0;       

        // Teste 1: Carrega um valor em cada registrador
        $display("Test 1: Loading values in all registers...");
        for (i = 0; i < 8; i++) begin
            addr_a = i[2:0]; // endereço do registrador 3 bits menos significativos de i
            load = 1;
            d_in = 8'b10101010+addr_a; // valor a ser carregado no registrador A
            #10 load = 0;
            #10; //espera pra ver o resultado
            $display("Address A: %d, Address B: %d, d_in: %b, out_a: %b, out_b: %b, load: %b", addr_a, addr_b, d_in, out_a, out_b, load);
        end
        $display("Test 1 done!");

        
        $display("Test 2: Resetting one register...");
        // Teste 2: Reseta o endereço de um registrador
        addr_a = 3'b000;   
        addr_b = 3'b001;
        reset = 1;
        #10 reset = 0;
        #10; //espera pra ver o resultado
        $display("Address A: %d, Address B: %d, d_in: %b, out_a: %b, out_b: %b, load: %b", addr_a, addr_b, d_in, out_a, out_b, load);
        $display("Test 2 done!");

        $display("Test 3: Changing input without changing load...");
        // Teste 3: Coloca outro valor na entrada sem alterar o load
        #10 d_in = 8'b11001100;
        $display("Address A: %d, Address B: %d, d_in: %b, out_a: %b, out_b: %b, load: %b", addr_a, addr_b, d_in, out_a, out_b, load);
        $display("Test 3 done!");

        $display("Test 4: Changing load and varying address to change register value...");
        // Teste 4: Altera o load e varia o endereço para alterar o valor do registrador
        #5 load = 1;
        for (i = 0; i < 8; i++) begin
            #10 addr_a = i[2:0];
            $display("Address A: %d, Address B: %d, d_in: %b, out_a: %b, out_b: %b, load: %b", addr_a, addr_b, d_in, out_a, out_b, load);
        end
        #5 load = 0;
        $display("Test 4 done!");

        $display("Test 5: Put a constant as val_b...");
        // Teste 5: Coloca um valor constante em val_b
        #10 addr_b = 3'b001;
        mb_select = 1;
        $display("Address A: %d, Address B: %d, d_in: %b, out_a: %b, out_b: %b, load: %b", addr_a, addr_b, d_in, out_a, out_b, load);
        $display("Test 6 done!");


        $display("Test 6: Reset all registers...");
        // Teste 6: Aplica reset_all (deve zerar o registrador mesmo sem estar na borda positiva do clock)
        #10 reset_all = 1;
        #10 reset_all = 0;
        $display("Test 6 done!");

        $display("Test finished! :D");

        #50 $finish;
    end

endmodule

src/test/test_outputs/test_FileRegister.vcd
$date
	Thu Aug 22 12:06:19 2024
$end
$version
	Icarus Verilog
$end
$timescale
	1s
$end
$scope module registerFile_testbench $end
$var wire 8 ! out_b [7:0] $end
$var wire 8 " out_a [7:0] $end
$var reg 3 # addr_a [2:0] $end
$var reg 3 $ addr_b [2:0] $end
$var reg 1 % clk $end
$var reg 8 & d_in [7:0] $end
$var reg 1 ' load $end
$var reg 1 ( mb_select $end
$var reg 1 ) reset $end
$var reg 1 * reset_all $end
$var integer 32 + i [31:0] $end
$scope module test_register $end
$var wire 3 , addr_a [2:0] $end
$var wire 3 - addr_b [2:0] $end
$var wire 1 % clk $end
$var wire 8 . d_in [7:0] $end
$var wire 1 ' load $end
$var wire 1 ( mb_select $end
$var wire 1 ) reset $end
$var wire 1 * reset_all $end
$var reg 8 / val_a [7:0] $end
$var reg 8 0 val_b [7:0] $end
$var integer 32 1 i [31:0] $end
$upscope $end
$upscope $end
$enddefinitions $end
#0
$dumpvars
bx 1
bx 0
bx /
b0 .
b0 -
b0 ,
bx +
0*
0)
0(
0'
b0 &
0%
b0 $
b0 #
bx "
bx !
$end
#5
1%
#10
0%
1*
#15
b0 !
b0 0
b0 "
b0 /
b1000 1
1%
#20
0%
b10101010 &
b10101010 .
1'
b0 +
0*
#25
b10101010 !
b10101010 0
b10101010 "
b10101010 /
1%
#30
0%
0'
#35
1%
#40
b0 "
b0 /
0%
b10101011 &
b10101011 .
1'
b1 #
b1 ,
b1 +
#45
b10101011 "
b10101011 /
1%
#50
0%
0'
#55
1%
#60
b0 "
b0 /
0%
b10101100 &
b10101100 .
1'
b10 #
b10 ,
b10 +
#65
b10101100 "
b10101100 /
1%
#70
0%
0'
#75
1%
#80
b0 "
b0 /
0%
b10101101 &
b10101101 .
1'
b11 #
b11 ,
b11 +
#85
b10101101 "
b10101101 /
1%
#90
0%
0'
#95
1%
#100
b0 "
b0 /
0%
b10101110 &
b10101110 .
1'
b100 #
b100 ,
b100 +
#105
b10101110 "
b10101110 /
1%
#110
0%
0'
#115
1%
#120
b0 "
b0 /
0%
b10101111 &
b10101111 .
1'
b101 #
b101 ,
b101 +
#125
b10101111 "
b10101111 /
1%
#130
0%
0'
#135
1%
#140
b0 "
b0 /
0%
b10110000 &
b10110000 .
1'
b110 #
b110 ,
b110 +
#145
b10110000 "
b10110000 /
1%
#150
0%
0'
#155
1%
#160
b0 "
b0 /
0%
b10110001 &
b10110001 .
1'
b111 #
b111 ,
b111 +
#165
b10110001 "
b10110001 /
1%
#170
0%
0'
#175
1%
#180
b10101011 !
b10101011 0
b0 "
b0 /
0%
1)
b1 $
b1 -
b0 #
b0 ,
b1000 +
#185
1%
#190
0%
0)
#195
1%
#200
0%
#205
1%
#210
0%
b11001100 &
b11001100 .
#215
b11001100 "
b11001100 /
1%
b0 +
1'
#220
0%
#225
1%
b1 +
#230
0%
#235
b11001100 !
b11001100 0
b11001100 "
b11001100 /
1%
b10 +
b1 #
b1 ,
#240
0%
#245
b11001100 "
b11001100 /
1%
b11 +
b10 #
b10 ,
#250
0%
#255
b11001100 "
b11001100 /
1%
b100 +
b11 #
b11 ,
#260
0%
#265
b11001100 "
b11001100 /
1%
b101 +
b100 #
b100 ,
#270
0%
#275
b11001100 "
b11001100 /
1%
b110 +
b101 #
b101 ,
#280
0%
#285
b11001100 "
b11001100 /
1%
b111 +
b110 #
b110 ,
#290
0%
#295
b11001100 "
b11001100 /
1%
b1000 +
b111 #
b111 ,
#300
0%
0'
#305
1%
#310
b1 !
b1 0
0%
1(
#315
1%
#320
0%
1*
#325
b0 "
b0 /
b1000 1
1%
#330
0%
0*
